sphinxscript/__init__.py
sphinxscript/document.py
sphinxscript/parsers.py
sphinxscript-0.0.6.dist-info/DESCRIPTION.rst
sphinxscript-0.0.6.dist-info/METADATA
sphinxscript-0.0.6.dist-info/RECORD
sphinxscript-0.0.6.dist-info/WHEEL
sphinxscript-0.0.6.dist-info/metadata.json
sphinxscript-0.0.6.dist-info/top_level.txt
