Metadata-Version: 2.0
Name: sphinxscript
Version: 0.0.6
Summary: Tool for building restructured text documentation for projects with scripts in many languages
Home-page: https://github.com/ClimateImpactLab/sphinxscript
Author: Climate Impact Lab
Author-email: delgado.michaelt@gmail.com
License: BSD
Download-URL: https://github.com/ClimateImpactLab/sphinxscript/tarball/0.0.6
Platform: UNKNOWN
Classifier: Development Status :: 3 - Alpha
Classifier: Intended Audience :: Developers
Classifier: Programming Language :: Python :: 3
Requires-Dist: coverage
Requires-Dist: nose
Requires-Dist: pypi-publisher
Requires-Dist: sphinx
Requires-Dist: sphinx-rtd-theme
